{
  "head" : {
    "vars" : [ "website", "email", "phone", "citizensInitiatives", "foiUrl", "contactPage", "regulatoryText", "regulatoryTextTitle", "leadBy", "parent", "wikipedia" ]
  },
  "results" : {
    "bindings" : [ {
      "website" : {
        "type" : "uri",
        "value" : "https://www.mfa.gov.lv/austria"
      },
      "email" : {
        "type" : "uri",
        "value" : "mailto:embassy.austria@mfa.gov.lv"
      },
      "phone" : {
        "type" : "literal",
        "value" : "+43-1-403-31-12"
      }
    } ]
  }
}