{
  "head" : {
    "vars" : [ "website", "email", "phone", "citizensInitiatives", "foiUrl", "contactPage", "regulatoryText", "regulatoryTextTitle", "leadBy", "parent", "wikipedia" ]
  },
  "results" : {
    "bindings" : [ {
      "wikipedia" : {
        "type" : "uri",
        "value" : "https://en.wikipedia.org/wiki/Morlanwelz"
      },
      "website" : {
        "type" : "uri",
        "value" : "https://www.morlanwelz.be"
      },
      "email" : {
        "type" : "uri",
        "value" : "mailto:info@morlanwelz.be"
      },
      "phone" : {
        "type" : "literal",
        "value" : "+32-64-43-17-17"
      },
      "leadBy" : {
        "xml:lang" : "en",
        "type" : "literal",
        "value" : "Christian Moureau"
      }
    } ]
  }
}