{
  "head" : {
    "vars" : [ "platformLabel", "property", "url", "account" ]
  },
  "results" : {
    "bindings" : [ {
      "platformLabel" : {
        "xml:lang" : "en",
        "type" : "literal",
        "value" : "YouTube"
      },
      "property" : {
        "type" : "uri",
        "value" : "http://www.wikidata.org/entity/P11245"
      },
      "url" : {
        "type" : "uri",
        "value" : "https://www.youtube.com/@u.s.embassyuganda"
      },
      "account" : {
        "type" : "literal",
        "value" : "u.s.embassyuganda"
      }
    }, {
      "platformLabel" : {
        "xml:lang" : "en",
        "type" : "literal",
        "value" : "X"
      },
      "property" : {
        "type" : "uri",
        "value" : "http://www.wikidata.org/entity/P2002"
      },
      "url" : {
        "type" : "uri",
        "value" : "https://x.com/usembassyuganda"
      },
      "account" : {
        "type" : "literal",
        "value" : "usembassyuganda"
      }
    }, {
      "platformLabel" : {
        "xml:lang" : "en",
        "type" : "literal",
        "value" : "Instagram"
      },
      "property" : {
        "type" : "uri",
        "value" : "http://www.wikidata.org/entity/P2003"
      },
      "url" : {
        "type" : "uri",
        "value" : "https://www.instagram.com/usembassyuganda/"
      },
      "account" : {
        "type" : "literal",
        "value" : "usembassyuganda"
      }
    }, {
      "platformLabel" : {
        "xml:lang" : "en",
        "type" : "literal",
        "value" : "Facebook"
      },
      "property" : {
        "type" : "uri",
        "value" : "http://www.wikidata.org/entity/P2013"
      },
      "url" : {
        "type" : "uri",
        "value" : "https://www.facebook.com/USEmbassyUganda"
      },
      "account" : {
        "type" : "literal",
        "value" : "USEmbassyUganda"
      }
    }, {
      "platformLabel" : {
        "xml:lang" : "en",
        "type" : "literal",
        "value" : "YouTube"
      },
      "property" : {
        "type" : "uri",
        "value" : "http://www.wikidata.org/entity/P2397"
      },
      "url" : {
        "type" : "uri",
        "value" : "https://www.youtube.com/channel/UC1wHpXjasgda0pzk_20uSsg"
      },
      "account" : {
        "type" : "literal",
        "value" : "UC1wHpXjasgda0pzk_20uSsg"
      }
    }, {
      "platformLabel" : {
        "xml:lang" : "en",
        "type" : "literal",
        "value" : "Flickr"
      },
      "property" : {
        "type" : "uri",
        "value" : "http://www.wikidata.org/entity/P3267"
      },
      "url" : {
        "type" : "uri",
        "value" : "https://www.flickr.com/people/54621517@N08"
      },
      "account" : {
        "type" : "literal",
        "value" : "54621517@N08"
      }
    } ]
  }
}