{
  "head" : {
    "vars" : [ "platformLabel", "property", "url", "account" ]
  },
  "results" : {
    "bindings" : [ {
      "platformLabel" : {
        "xml:lang" : "en",
        "type" : "literal",
        "value" : "X"
      },
      "property" : {
        "type" : "uri",
        "value" : "http://www.wikidata.org/entity/P2002"
      },
      "url" : {
        "type" : "uri",
        "value" : "https://x.com/Land_SH"
      },
      "account" : {
        "type" : "literal",
        "value" : "Land_SH"
      }
    }, {
      "platformLabel" : {
        "xml:lang" : "en",
        "type" : "literal",
        "value" : "Facebook"
      },
      "property" : {
        "type" : "uri",
        "value" : "http://www.wikidata.org/entity/P2013"
      },
      "url" : {
        "type" : "uri",
        "value" : "https://www.facebook.com/SchleswigHolstein"
      },
      "account" : {
        "type" : "literal",
        "value" : "SchleswigHolstein"
      }
    }, {
      "platformLabel" : {
        "xml:lang" : "en",
        "type" : "literal",
        "value" : "Mastodon"
      },
      "property" : {
        "type" : "uri",
        "value" : "http://www.wikidata.org/entity/P4033"
      },
      "url" : {
        "type" : "uri",
        "value" : "https://fedirect.toolforge.org/?id=landesregierung@social.schleswig-holstein.de"
      },
      "account" : {
        "type" : "literal",
        "value" : "landesregierung@social.schleswig-holstein.de"
      }
    } ]
  }
}