{
  "head" : {
    "vars" : [ "platformLabel", "property", "url", "account" ]
  },
  "results" : {
    "bindings" : [ {
      "platformLabel" : {
        "xml:lang" : "en",
        "type" : "literal",
        "value" : "YouTube"
      },
      "property" : {
        "type" : "uri",
        "value" : "http://www.wikidata.org/entity/P11245"
      },
      "url" : {
        "type" : "uri",
        "value" : "https://www.youtube.com/@deinlandsteiermark"
      },
      "account" : {
        "type" : "literal",
        "value" : "deinlandsteiermark"
      }
    }, {
      "platformLabel" : {
        "xml:lang" : "en",
        "type" : "literal",
        "value" : "Instagram"
      },
      "property" : {
        "type" : "uri",
        "value" : "http://www.wikidata.org/entity/P2003"
      },
      "url" : {
        "type" : "uri",
        "value" : "https://www.instagram.com/land_steiermark/"
      },
      "account" : {
        "type" : "literal",
        "value" : "land_steiermark"
      }
    }, {
      "platformLabel" : {
        "xml:lang" : "en",
        "type" : "literal",
        "value" : "Facebook"
      },
      "property" : {
        "type" : "uri",
        "value" : "http://www.wikidata.org/entity/P2013"
      },
      "url" : {
        "type" : "uri",
        "value" : "https://www.facebook.com/steiermark"
      },
      "account" : {
        "type" : "literal",
        "value" : "steiermark"
      }
    }, {
      "platformLabel" : {
        "xml:lang" : "en",
        "type" : "literal",
        "value" : "YouTube"
      },
      "property" : {
        "type" : "uri",
        "value" : "http://www.wikidata.org/entity/P2397"
      },
      "url" : {
        "type" : "uri",
        "value" : "https://www.youtube.com/channel/UCaV4I-ukpvLV7F8gYZki_TQ"
      },
      "account" : {
        "type" : "literal",
        "value" : "UCaV4I-ukpvLV7F8gYZki_TQ"
      }
    } ]
  }
}