{
  "head" : {
    "vars" : [ "platformLabel", "property", "url", "account" ]
  },
  "results" : {
    "bindings" : [ {
      "platformLabel" : {
        "xml:lang" : "en",
        "type" : "literal",
        "value" : "YouTube"
      },
      "property" : {
        "type" : "uri",
        "value" : "http://www.wikidata.org/entity/P11245"
      },
      "url" : {
        "type" : "uri",
        "value" : "https://www.youtube.com/@singaporeusembassy"
      },
      "account" : {
        "type" : "literal",
        "value" : "singaporeusembassy"
      }
    }, {
      "platformLabel" : {
        "xml:lang" : "en",
        "type" : "literal",
        "value" : "X"
      },
      "property" : {
        "type" : "uri",
        "value" : "http://www.wikidata.org/entity/P2002"
      },
      "url" : {
        "type" : "uri",
        "value" : "https://x.com/USEmbassySG"
      },
      "account" : {
        "type" : "literal",
        "value" : "USEmbassySG"
      }
    }, {
      "platformLabel" : {
        "xml:lang" : "en",
        "type" : "literal",
        "value" : "Instagram"
      },
      "property" : {
        "type" : "uri",
        "value" : "http://www.wikidata.org/entity/P2003"
      },
      "url" : {
        "type" : "uri",
        "value" : "https://www.instagram.com/usembassysingapore/"
      },
      "account" : {
        "type" : "literal",
        "value" : "usembassysingapore"
      }
    }, {
      "platformLabel" : {
        "xml:lang" : "en",
        "type" : "literal",
        "value" : "Facebook"
      },
      "property" : {
        "type" : "uri",
        "value" : "http://www.wikidata.org/entity/P2013"
      },
      "url" : {
        "type" : "uri",
        "value" : "https://www.facebook.com/singapore.usembassy"
      },
      "account" : {
        "type" : "literal",
        "value" : "singapore.usembassy"
      }
    }, {
      "platformLabel" : {
        "xml:lang" : "en",
        "type" : "literal",
        "value" : "YouTube"
      },
      "property" : {
        "type" : "uri",
        "value" : "http://www.wikidata.org/entity/P2397"
      },
      "url" : {
        "type" : "uri",
        "value" : "https://www.youtube.com/channel/UCyUGF787fCke2SFAmbQqbPg"
      },
      "account" : {
        "type" : "literal",
        "value" : "UCyUGF787fCke2SFAmbQqbPg"
      }
    }, {
      "platformLabel" : {
        "xml:lang" : "en",
        "type" : "literal",
        "value" : "Flickr"
      },
      "property" : {
        "type" : "uri",
        "value" : "http://www.wikidata.org/entity/P3267"
      },
      "url" : {
        "type" : "uri",
        "value" : "https://www.flickr.com/people/60040239@N05"
      },
      "account" : {
        "type" : "literal",
        "value" : "60040239@N05"
      }
    }, {
      "platformLabel" : {
        "xml:lang" : "en",
        "type" : "literal",
        "value" : "LinkedIn"
      },
      "property" : {
        "type" : "uri",
        "value" : "http://www.wikidata.org/entity/P4264"
      },
      "url" : {
        "type" : "uri",
        "value" : "https://www.linkedin.com/company/usembassysingapore"
      },
      "account" : {
        "type" : "literal",
        "value" : "usembassysingapore"
      }
    } ]
  }
}