{
  "head" : {
    "vars" : [ "platformLabel", "property", "url", "account" ]
  },
  "results" : {
    "bindings" : [ {
      "platformLabel" : {
        "xml:lang" : "en",
        "type" : "literal",
        "value" : "X"
      },
      "property" : {
        "type" : "uri",
        "value" : "http://www.wikidata.org/entity/P2002"
      },
      "url" : {
        "type" : "uri",
        "value" : "https://x.com/EgovBg"
      },
      "account" : {
        "type" : "literal",
        "value" : "EgovBg"
      }
    }, {
      "platformLabel" : {
        "xml:lang" : "en",
        "type" : "literal",
        "value" : "Facebook"
      },
      "property" : {
        "type" : "uri",
        "value" : "http://www.wikidata.org/entity/P2013"
      },
      "url" : {
        "type" : "uri",
        "value" : "https://www.facebook.com/ministryofelectronicgovernance"
      },
      "account" : {
        "type" : "literal",
        "value" : "ministryofelectronicgovernance"
      }
    }, {
      "platformLabel" : {
        "xml:lang" : "en",
        "type" : "literal",
        "value" : "YouTube"
      },
      "property" : {
        "type" : "uri",
        "value" : "http://www.wikidata.org/entity/P2397"
      },
      "url" : {
        "type" : "uri",
        "value" : "https://www.youtube.com/channel/UCDtE00i5yJ1uMii00rrhhbg"
      },
      "account" : {
        "type" : "literal",
        "value" : "UCDtE00i5yJ1uMii00rrhhbg"
      }
    }, {
      "platformLabel" : {
        "xml:lang" : "en",
        "type" : "literal",
        "value" : "LinkedIn"
      },
      "property" : {
        "type" : "uri",
        "value" : "http://www.wikidata.org/entity/P4264"
      },
      "url" : {
        "type" : "uri",
        "value" : "https://www.linkedin.com/company/egov-bg"
      },
      "account" : {
        "type" : "literal",
        "value" : "egov-bg"
      }
    } ]
  }
}