{
  "head" : {
    "vars" : [ "platformLabel", "property", "url", "account" ]
  },
  "results" : {
    "bindings" : [ {
      "platformLabel" : {
        "xml:lang" : "en",
        "type" : "literal",
        "value" : "YouTube"
      },
      "property" : {
        "type" : "uri",
        "value" : "http://www.wikidata.org/entity/P11245"
      },
      "url" : {
        "type" : "uri",
        "value" : "https://www.youtube.com/@kopingskommun"
      },
      "account" : {
        "type" : "literal",
        "value" : "kopingskommun"
      }
    }, {
      "platformLabel" : {
        "xml:lang" : "en",
        "type" : "literal",
        "value" : "X"
      },
      "property" : {
        "type" : "uri",
        "value" : "http://www.wikidata.org/entity/P2002"
      },
      "url" : {
        "type" : "uri",
        "value" : "https://x.com/Kopings_kommun"
      },
      "account" : {
        "type" : "literal",
        "value" : "Kopings_kommun"
      }
    }, {
      "platformLabel" : {
        "xml:lang" : "en",
        "type" : "literal",
        "value" : "Instagram"
      },
      "property" : {
        "type" : "uri",
        "value" : "http://www.wikidata.org/entity/P2003"
      },
      "url" : {
        "type" : "uri",
        "value" : "https://www.instagram.com/kopings_kommun/"
      },
      "account" : {
        "type" : "literal",
        "value" : "kopings_kommun"
      }
    }, {
      "platformLabel" : {
        "xml:lang" : "en",
        "type" : "literal",
        "value" : "Facebook"
      },
      "property" : {
        "type" : "uri",
        "value" : "http://www.wikidata.org/entity/P2013"
      },
      "url" : {
        "type" : "uri",
        "value" : "https://www.facebook.com/Kopingskommun"
      },
      "account" : {
        "type" : "literal",
        "value" : "Kopingskommun"
      }
    }, {
      "platformLabel" : {
        "xml:lang" : "en",
        "type" : "literal",
        "value" : "YouTube"
      },
      "property" : {
        "type" : "uri",
        "value" : "http://www.wikidata.org/entity/P2397"
      },
      "url" : {
        "type" : "uri",
        "value" : "https://www.youtube.com/channel/UCjlo4CYh6XHKkzVhfAFoN5g"
      },
      "account" : {
        "type" : "literal",
        "value" : "UCjlo4CYh6XHKkzVhfAFoN5g"
      }
    }, {
      "platformLabel" : {
        "xml:lang" : "en",
        "type" : "literal",
        "value" : "LinkedIn"
      },
      "property" : {
        "type" : "uri",
        "value" : "http://www.wikidata.org/entity/P4264"
      },
      "url" : {
        "type" : "uri",
        "value" : "https://www.linkedin.com/company/kopings-kommun"
      },
      "account" : {
        "type" : "literal",
        "value" : "kopings-kommun"
      }
    } ]
  }
}