{
  "head" : {
    "vars" : [ "platformLabel", "property", "url", "account" ]
  },
  "results" : {
    "bindings" : [ {
      "platformLabel" : {
        "xml:lang" : "en",
        "type" : "literal",
        "value" : "X"
      },
      "property" : {
        "type" : "uri",
        "value" : "http://www.wikidata.org/entity/P2002"
      },
      "url" : {
        "type" : "uri",
        "value" : "https://x.com/CPB_Commission"
      },
      "account" : {
        "type" : "literal",
        "value" : "CPB_Commission"
      }
    }, {
      "platformLabel" : {
        "xml:lang" : "en",
        "type" : "literal",
        "value" : "Instagram"
      },
      "property" : {
        "type" : "uri",
        "value" : "http://www.wikidata.org/entity/P2003"
      },
      "url" : {
        "type" : "uri",
        "value" : "https://www.instagram.com/centralpinebarrenscommission/"
      },
      "account" : {
        "type" : "literal",
        "value" : "centralpinebarrenscommission"
      }
    }, {
      "platformLabel" : {
        "xml:lang" : "en",
        "type" : "literal",
        "value" : "Facebook"
      },
      "property" : {
        "type" : "uri",
        "value" : "http://www.wikidata.org/entity/P2013"
      },
      "url" : {
        "type" : "uri",
        "value" : "https://www.facebook.com/CentralPineBarrensCommission"
      },
      "account" : {
        "type" : "literal",
        "value" : "CentralPineBarrensCommission"
      }
    }, {
      "platformLabel" : {
        "xml:lang" : "en",
        "type" : "literal",
        "value" : "YouTube"
      },
      "property" : {
        "type" : "uri",
        "value" : "http://www.wikidata.org/entity/P2397"
      },
      "url" : {
        "type" : "uri",
        "value" : "https://www.youtube.com/channel/UCf5T2yzWwVyK2IVzIVpP_yw"
      },
      "account" : {
        "type" : "literal",
        "value" : "UCf5T2yzWwVyK2IVzIVpP_yw"
      }
    } ]
  }
}