{
  "head" : {
    "vars" : [ "platformLabel", "property", "url", "account" ]
  },
  "results" : {
    "bindings" : [ {
      "platformLabel" : {
        "xml:lang" : "en",
        "type" : "literal",
        "value" : "YouTube"
      },
      "property" : {
        "type" : "uri",
        "value" : "http://www.wikidata.org/entity/P11245"
      },
      "url" : {
        "type" : "uri",
        "value" : "https://www.youtube.com/@brandweerwesthoek"
      },
      "account" : {
        "type" : "literal",
        "value" : "brandweerwesthoek"
      }
    }, {
      "platformLabel" : {
        "xml:lang" : "en",
        "type" : "literal",
        "value" : "X"
      },
      "property" : {
        "type" : "uri",
        "value" : "http://www.wikidata.org/entity/P2002"
      },
      "url" : {
        "type" : "uri",
        "value" : "https://x.com/Brw_Westhoek"
      },
      "account" : {
        "type" : "literal",
        "value" : "Brw_Westhoek"
      }
    }, {
      "platformLabel" : {
        "xml:lang" : "en",
        "type" : "literal",
        "value" : "Facebook"
      },
      "property" : {
        "type" : "uri",
        "value" : "http://www.wikidata.org/entity/P2013"
      },
      "url" : {
        "type" : "uri",
        "value" : "https://www.facebook.com/brandweerwesthoek"
      },
      "account" : {
        "type" : "literal",
        "value" : "brandweerwesthoek"
      }
    }, {
      "platformLabel" : {
        "xml:lang" : "en",
        "type" : "literal",
        "value" : "YouTube"
      },
      "property" : {
        "type" : "uri",
        "value" : "http://www.wikidata.org/entity/P2397"
      },
      "url" : {
        "type" : "uri",
        "value" : "https://www.youtube.com/channel/UCDHRVG6rj6IIs0JBBXPSHgA"
      },
      "account" : {
        "type" : "literal",
        "value" : "UCDHRVG6rj6IIs0JBBXPSHgA"
      }
    }, {
      "platformLabel" : {
        "xml:lang" : "en",
        "type" : "literal",
        "value" : "LinkedIn"
      },
      "property" : {
        "type" : "uri",
        "value" : "http://www.wikidata.org/entity/P4264"
      },
      "url" : {
        "type" : "uri",
        "value" : "https://www.linkedin.com/company/brandweerwesthoek"
      },
      "account" : {
        "type" : "literal",
        "value" : "brandweerwesthoek"
      }
    }, {
      "platformLabel" : {
        "xml:lang" : "en",
        "type" : "literal",
        "value" : "TikTok"
      },
      "property" : {
        "type" : "uri",
        "value" : "http://www.wikidata.org/entity/P7085"
      },
      "url" : {
        "type" : "uri",
        "value" : "https://www.tiktok.com/@brandweer_westhoek"
      },
      "account" : {
        "type" : "literal",
        "value" : "brandweer_westhoek"
      }
    } ]
  }
}