{
  "head" : {
    "vars" : [ "platformLabel", "property", "url", "account" ]
  },
  "results" : {
    "bindings" : [ {
      "platformLabel" : {
        "xml:lang" : "en",
        "type" : "literal",
        "value" : "X"
      },
      "property" : {
        "type" : "uri",
        "value" : "http://www.wikidata.org/entity/P2002"
      },
      "url" : {
        "type" : "uri",
        "value" : "https://x.com/MKIPUkraine"
      },
      "account" : {
        "type" : "literal",
        "value" : "MKIPUkraine"
      }
    }, {
      "platformLabel" : {
        "xml:lang" : "en",
        "type" : "literal",
        "value" : "X"
      },
      "property" : {
        "type" : "uri",
        "value" : "http://www.wikidata.org/entity/P2002"
      },
      "url" : {
        "type" : "uri",
        "value" : "https://x.com/MCSCUkraine"
      },
      "account" : {
        "type" : "literal",
        "value" : "MCSCUkraine"
      }
    }, {
      "platformLabel" : {
        "xml:lang" : "en",
        "type" : "literal",
        "value" : "Instagram"
      },
      "property" : {
        "type" : "uri",
        "value" : "http://www.wikidata.org/entity/P2003"
      },
      "url" : {
        "type" : "uri",
        "value" : "https://www.instagram.com/mkip_ukraine/"
      },
      "account" : {
        "type" : "literal",
        "value" : "mkip_ukraine"
      }
    }, {
      "platformLabel" : {
        "xml:lang" : "en",
        "type" : "literal",
        "value" : "Instagram"
      },
      "property" : {
        "type" : "uri",
        "value" : "http://www.wikidata.org/entity/P2003"
      },
      "url" : {
        "type" : "uri",
        "value" : "https://www.instagram.com/mcsc_ukraine/"
      },
      "account" : {
        "type" : "literal",
        "value" : "mcsc_ukraine"
      }
    }, {
      "platformLabel" : {
        "xml:lang" : "en",
        "type" : "literal",
        "value" : "Facebook"
      },
      "property" : {
        "type" : "uri",
        "value" : "http://www.wikidata.org/entity/P2013"
      },
      "url" : {
        "type" : "uri",
        "value" : "https://www.facebook.com/MKIPUkraine"
      },
      "account" : {
        "type" : "literal",
        "value" : "MKIPUkraine"
      }
    }, {
      "platformLabel" : {
        "xml:lang" : "en",
        "type" : "literal",
        "value" : "Facebook"
      },
      "property" : {
        "type" : "uri",
        "value" : "http://www.wikidata.org/entity/P2013"
      },
      "url" : {
        "type" : "uri",
        "value" : "https://www.facebook.com/MCSCUkraine"
      },
      "account" : {
        "type" : "literal",
        "value" : "MCSCUkraine"
      }
    }, {
      "platformLabel" : {
        "xml:lang" : "en",
        "type" : "literal",
        "value" : "YouTube"
      },
      "property" : {
        "type" : "uri",
        "value" : "http://www.wikidata.org/entity/P2397"
      },
      "url" : {
        "type" : "uri",
        "value" : "https://www.youtube.com/channel/UCgLarZawhgHPjKy008t3Y2w"
      },
      "account" : {
        "type" : "literal",
        "value" : "UCgLarZawhgHPjKy008t3Y2w"
      }
    }, {
      "platformLabel" : {
        "xml:lang" : "mul",
        "type" : "literal",
        "value" : "Telegram"
      },
      "property" : {
        "type" : "uri",
        "value" : "http://www.wikidata.org/entity/P3789"
      },
      "url" : {
        "type" : "uri",
        "value" : "https://t.me/s/mcscukraine"
      },
      "account" : {
        "type" : "literal",
        "value" : "mcscukraine"
      }
    }, {
      "platformLabel" : {
        "xml:lang" : "en",
        "type" : "literal",
        "value" : "TikTok"
      },
      "property" : {
        "type" : "uri",
        "value" : "http://www.wikidata.org/entity/P7085"
      },
      "url" : {
        "type" : "uri",
        "value" : "https://www.tiktok.com/@mcip.ua"
      },
      "account" : {
        "type" : "literal",
        "value" : "mcip.ua"
      }
    } ]
  }
}