{
  "head" : {
    "vars" : [ "platformLabel", "property", "url", "account" ]
  },
  "results" : {
    "bindings" : [ {
      "platformLabel" : {
        "xml:lang" : "en",
        "type" : "literal",
        "value" : "YouTube"
      },
      "property" : {
        "type" : "uri",
        "value" : "http://www.wikidata.org/entity/P11245"
      },
      "url" : {
        "type" : "uri",
        "value" : "https://www.youtube.com/@valkeakoskenkaupunki"
      },
      "account" : {
        "type" : "literal",
        "value" : "valkeakoskenkaupunki"
      }
    }, {
      "platformLabel" : {
        "xml:lang" : "en",
        "type" : "literal",
        "value" : "Instagram"
      },
      "property" : {
        "type" : "uri",
        "value" : "http://www.wikidata.org/entity/P2003"
      },
      "url" : {
        "type" : "uri",
        "value" : "https://www.instagram.com/visitvalkeakoskiofficial/"
      },
      "account" : {
        "type" : "literal",
        "value" : "visitvalkeakoskiofficial"
      }
    }, {
      "platformLabel" : {
        "xml:lang" : "en",
        "type" : "literal",
        "value" : "Facebook"
      },
      "property" : {
        "type" : "uri",
        "value" : "http://www.wikidata.org/entity/P2013"
      },
      "url" : {
        "type" : "uri",
        "value" : "https://www.facebook.com/valkeakoskenkaupunki"
      },
      "account" : {
        "type" : "literal",
        "value" : "valkeakoskenkaupunki"
      }
    }, {
      "platformLabel" : {
        "xml:lang" : "en",
        "type" : "literal",
        "value" : "YouTube"
      },
      "property" : {
        "type" : "uri",
        "value" : "http://www.wikidata.org/entity/P2397"
      },
      "url" : {
        "type" : "uri",
        "value" : "https://www.youtube.com/channel/UCoQXn5_bO1GmJUz3VZdOrvw"
      },
      "account" : {
        "type" : "literal",
        "value" : "UCoQXn5_bO1GmJUz3VZdOrvw"
      }
    }, {
      "platformLabel" : {
        "xml:lang" : "en",
        "type" : "literal",
        "value" : "LinkedIn"
      },
      "property" : {
        "type" : "uri",
        "value" : "http://www.wikidata.org/entity/P4264"
      },
      "url" : {
        "type" : "uri",
        "value" : "https://www.linkedin.com/company/city-of-valkeakoski"
      },
      "account" : {
        "type" : "literal",
        "value" : "city-of-valkeakoski"
      }
    } ]
  }
}