{
  "head" : {
    "vars" : [ "platformLabel", "property", "url", "verified", "account" ]
  },
  "results" : {
    "bindings" : [ {
      "platformLabel" : {
        "xml:lang" : "en",
        "type" : "literal",
        "value" : "Twitter"
      },
      "property" : {
        "type" : "uri",
        "value" : "http://www.wikidata.org/entity/P2002"
      },
      "url" : {
        "type" : "uri",
        "value" : "https://twitter.com/NorwayinLebanon"
      },
      "verified" : {
        "datatype" : "http://www.w3.org/2001/XMLSchema#boolean",
        "type" : "literal",
        "value" : "false"
      },
      "account" : {
        "type" : "literal",
        "value" : "NorwayinLebanon"
      }
    }, {
      "platformLabel" : {
        "xml:lang" : "en",
        "type" : "literal",
        "value" : "Instagram"
      },
      "property" : {
        "type" : "uri",
        "value" : "http://www.wikidata.org/entity/P2003"
      },
      "url" : {
        "type" : "uri",
        "value" : "https://www.instagram.com/norwayinlebanon/"
      },
      "verified" : {
        "datatype" : "http://www.w3.org/2001/XMLSchema#boolean",
        "type" : "literal",
        "value" : "false"
      },
      "account" : {
        "type" : "literal",
        "value" : "norwayinlebanon"
      }
    }, {
      "platformLabel" : {
        "xml:lang" : "en",
        "type" : "literal",
        "value" : "Facebook"
      },
      "property" : {
        "type" : "uri",
        "value" : "http://www.wikidata.org/entity/P2013"
      },
      "url" : {
        "type" : "uri",
        "value" : "https://www.facebook.com/norwegianembassybeirut"
      },
      "verified" : {
        "datatype" : "http://www.w3.org/2001/XMLSchema#boolean",
        "type" : "literal",
        "value" : "false"
      },
      "account" : {
        "type" : "literal",
        "value" : "norwegianembassybeirut"
      }
    } ]
  }
}