{
  "head" : {
    "vars" : [ "platformLabel", "property", "url", "verified", "account" ]
  },
  "results" : {
    "bindings" : [ {
      "platformLabel" : {
        "xml:lang" : "en",
        "type" : "literal",
        "value" : "Twitter"
      },
      "property" : {
        "type" : "uri",
        "value" : "http://www.wikidata.org/entity/P2002"
      },
      "url" : {
        "type" : "uri",
        "value" : "https://twitter.com/BIRA_IASB"
      },
      "verified" : {
        "datatype" : "http://www.w3.org/2001/XMLSchema#boolean",
        "type" : "literal",
        "value" : "false"
      },
      "account" : {
        "type" : "literal",
        "value" : "BIRA_IASB"
      }
    }, {
      "platformLabel" : {
        "xml:lang" : "en",
        "type" : "literal",
        "value" : "Instagram"
      },
      "property" : {
        "type" : "uri",
        "value" : "http://www.wikidata.org/entity/P2003"
      },
      "url" : {
        "type" : "uri",
        "value" : "https://www.instagram.com/bira_iasb/"
      },
      "verified" : {
        "datatype" : "http://www.w3.org/2001/XMLSchema#boolean",
        "type" : "literal",
        "value" : "false"
      },
      "account" : {
        "type" : "literal",
        "value" : "bira_iasb"
      }
    }, {
      "platformLabel" : {
        "xml:lang" : "en",
        "type" : "literal",
        "value" : "Facebook"
      },
      "property" : {
        "type" : "uri",
        "value" : "http://www.wikidata.org/entity/P2013"
      },
      "url" : {
        "type" : "uri",
        "value" : "https://www.facebook.com/BIRA.IASB"
      },
      "verified" : {
        "datatype" : "http://www.w3.org/2001/XMLSchema#boolean",
        "type" : "literal",
        "value" : "false"
      },
      "account" : {
        "type" : "literal",
        "value" : "BIRA.IASB"
      }
    }, {
      "platformLabel" : {
        "xml:lang" : "en",
        "type" : "literal",
        "value" : "YouTube"
      },
      "property" : {
        "type" : "uri",
        "value" : "http://www.wikidata.org/entity/P2397"
      },
      "url" : {
        "type" : "uri",
        "value" : "https://www.youtube.com/channel/UC5zMdZ_xAwijOjr5jwiJntw"
      },
      "verified" : {
        "datatype" : "http://www.w3.org/2001/XMLSchema#boolean",
        "type" : "literal",
        "value" : "false"
      },
      "account" : {
        "type" : "literal",
        "value" : "UC5zMdZ_xAwijOjr5jwiJntw"
      }
    }, {
      "platformLabel" : {
        "xml:lang" : "en",
        "type" : "literal",
        "value" : "Vimeo"
      },
      "property" : {
        "type" : "uri",
        "value" : "http://www.wikidata.org/entity/P4015"
      },
      "url" : {
        "type" : "uri",
        "value" : "https://vimeo.com/user27720425"
      },
      "verified" : {
        "datatype" : "http://www.w3.org/2001/XMLSchema#boolean",
        "type" : "literal",
        "value" : "false"
      },
      "account" : {
        "type" : "literal",
        "value" : "user27720425"
      }
    }, {
      "platformLabel" : {
        "xml:lang" : "en",
        "type" : "literal",
        "value" : "LinkedIn"
      },
      "property" : {
        "type" : "uri",
        "value" : "http://www.wikidata.org/entity/P4264"
      },
      "url" : {
        "type" : "uri",
        "value" : "https://www.linkedin.com/company/belgian-institute-for-space-aeronomy/"
      },
      "verified" : {
        "datatype" : "http://www.w3.org/2001/XMLSchema#boolean",
        "type" : "literal",
        "value" : "false"
      },
      "account" : {
        "type" : "literal",
        "value" : "belgian-institute-for-space-aeronomy"
      }
    } ]
  }
}